sqlstride/__about__.py
sqlstride/__init__.py
sqlstride/cli.py
sqlstride/config.py
sqlstride/constants.py
sqlstride/commands/__init__.py
sqlstride/commands/create_repo.py
sqlstride/commands/sync.py
sqlstride/database/__init__.py
sqlstride/database/connector_proxy.py
sqlstride/database/database_object.py
sqlstride/database/adapters/__init__.py
sqlstride/database/adapters/base.py
sqlstride/database/adapters/mariadb.py
sqlstride/database/adapters/mssql.py
sqlstride/database/adapters/postgres.py
sqlstride/file_utils/__init__.py
sqlstride/file_utils/parser.py
sqlstride/file_utils/templating.py
sqlstride-0.1.11.dist-info/METADATA
sqlstride-0.1.11.dist-info/WHEEL
sqlstride-0.1.11.dist-info/entry_points.txt
sqlstride-0.1.11.dist-info/licenses/LICENSE
sqlstride-0.1.11.dist-info/RECORD
