Metadata-Version: 2.4
Name: sqlstride
Version: 0.1.11
Summary: Zero-boilerplate schema migrations —straight from your own SQL files.
Project-URL: Documentation, https://github.com/magicjedi90/sqlstride#readme
Project-URL: Issues, https://github.com/magicjedi90/sqlstride/issues
Project-URL: Source, https://github.com/magicjedi90/sqlstride
Author-email: Jesse <magicjedi90@aim.com>
License-Expression: MIT
License-File: LICENSE
Keywords: database,database-migrations,db,db-migrations,migrations,repo,source-control
Classifier: Development Status :: 4 - Beta
Classifier: Programming Language :: Python
Classifier: Programming Language :: Python :: 3.8
Classifier: Programming Language :: Python :: 3.9
Classifier: Programming Language :: Python :: 3.10
Classifier: Programming Language :: Python :: 3.11
Classifier: Programming Language :: Python :: 3.12
Classifier: Programming Language :: Python :: 3.13
Classifier: Programming Language :: Python :: Implementation :: CPython
Classifier: Programming Language :: Python :: Implementation :: PyPy
Requires-Python: >=3.8
Requires-Dist: click
Requires-Dist: etl-utilities>=1.0.2
Requires-Dist: jinja2
Requires-Dist: pymysql
Requires-Dist: pyodbc
Requires-Dist: pyyaml
Requires-Dist: sqlparse
